markdown_html_finder-0.2.5.dist-info/METADATA
markdown_html_finder-0.2.5.dist-info/WHEEL
markdown_html_finder/__init__.py
markdown_html_finder/markdown_html_finder.cpython-310-x86_64-linux-gnu.so
markdown_html_finder-0.2.5.dist-info/RECORD
