Metadata-Version: 2.1
Name: markdown-html-finder
Version: 0.2.5
Summary: A Python library to find html in strings
Keywords: html
Author: 
Project-URL: Source Code, https://github.com/chdsbd/markdown-html-finder
